brimfile/__init__.py
brimfile/constants.py
brimfile/data.py
brimfile/file.py
brimfile/file_abstraction.py
brimfile/metadata.py
brimfile/units.py
brimfile/utils.py
brimfile/converter/__init__.py
brimfile/converter/brim_converter.py
brimfile/converter/hdf5_flattener.py
brimfile-1.3.3.dist-info/METADATA
brimfile-1.3.3.dist-info/WHEEL
brimfile-1.3.3.dist-info/licenses/LICENSE.toml
brimfile-1.3.3.dist-info/RECORD
